odoo10_addon_l10n_it_ateco-10.0.1.0.0-py2.7-nspkg.pth
odoo10_addon_l10n_it_ateco-10.0.1.0.0.dist-info/top_level.txt
odoo10_addon_l10n_it_ateco-10.0.1.0.0.dist-info/WHEEL
odoo10_addon_l10n_it_ateco-10.0.1.0.0.dist-info/RECORD
odoo10_addon_l10n_it_ateco-10.0.1.0.0.dist-info/metadata.json
odoo10_addon_l10n_it_ateco-10.0.1.0.0.dist-info/DESCRIPTION.rst
odoo10_addon_l10n_it_ateco-10.0.1.0.0.dist-info/METADATA
odoo10_addon_l10n_it_ateco-10.0.1.0.0.dist-info/namespace_packages.txt
odoo/addons/l10n_it_ateco/__manifest__.py
odoo/addons/l10n_it_ateco/__init__.py
odoo/addons/l10n_it_ateco/README.rst
odoo/addons/l10n_it_ateco/security/ir.model.access.csv
odoo/addons/l10n_it_ateco/view/ateco_view.xml
odoo/addons/l10n_it_ateco/view/partner_view.xml
odoo/addons/l10n_it_ateco/i18n/it.po
odoo/addons/l10n_it_ateco/i18n/l10n_it_ateco.pot
odoo/addons/l10n_it_ateco/model/ateco.py
odoo/addons/l10n_it_ateco/model/partner.py
odoo/addons/l10n_it_ateco/model/__init__.py
odoo/addons/l10n_it_ateco/data/ateco_data.xml
